{
  "label": "select builder",
  "goal": "build an assimilator",

  "memory": {
    "nodes": {
      "VESPENE": { "unitType": "vespene" },
      "PROBE": { "unitType": "probe", "busy": false },
      "SELECTION": { "unitType": "probe" }
    },

    "paths": [
      { "path": ["PROBE"] },
      { "path": ["GOAL", "vespene", "VESPENE"] },
      { "path": ["GOAL", "builder", "SELECTION"], "optional": true },
      {
        "label": "SELECT",
        "path": ["GOAL", "builder", "PROBE"],
        "provisional": true,
        "unique": true
      }
    ]
  },

  "input": [
    "VESPENE/x",
    "VESPENE/y",
    "SELECTION",
    "PROBE/x",
    "PROBE/y"
  ],

  "output": [
    "SELECT",
    "PROBE/busy"
  ]
}
