{
  "label": "harvest minerals",

  "given": {
    "nodes": {
      "GAME": { "label": "Game" }
    },
    "infos": [
      { "node": "GAME" }
    ]
  },

  "when": {
    "nodes": {
      "MINERALS": { "type": "mineral", "isUtilized": false },
      "PROBE": { "type:probe": true, "isProducer": false, "harvest": false, "isMobilized": false }
    },
    "infos": [
      { "node": "MINERALS", "label": "distanceToNexus" },
      { "node": "MINERALS", "label": "x" },
      { "node": "MINERALS", "label": "y" },
      { "node": "PROBE", "label": "x" },
      { "node": "PROBE", "label": "y" }
    ]
  },

  "then": {
    "paths": {
      "COMMAND": [ "PROBE", "harvest", "MINERALS" ]
    },
    "infos": [
      { "path": "COMMAND" }
    ]
  }

}
